defKey/__init__.py
defKey/defKey.py
defKey/getch.py
defKey-1.0.1.dist-info/LICENSE
defKey-1.0.1.dist-info/METADATA
defKey-1.0.1.dist-info/WHEEL
defKey-1.0.1.dist-info/top_level.txt
defKey-1.0.1.dist-info/RECORD
