Metadata-Version: 2.1
Name: defKey
Version: 1.0.1
Summary: Non-blocking keybinds using threads
Home-page: https://github.com/a11ce/defKey
Author: Riley/a11ce
Author-email: a11ce@protonmail.com
License: UNKNOWN
Platform: UNKNOWN
Requires-Python: >=3.6
